multineuronchat/MultiNeuronChat.py
multineuronchat/MultiNeuronChatObject.py
multineuronchat/__init__.py
multineuronchat/loompy_utils.py
multineuronchat/masks.py
multineuronchat/normalize.py
multineuronchat/utils.py
multineuronchat/visualize.py
multineuronchat/InteractionDB/InteractionDB.py
multineuronchat/InteractionDB/InteractionDBRow.py
multineuronchat/InteractionDB/__init__.py
multineuronchat/db/__init__.py
multineuronchat-2025.11.14.dist-info/licenses/LICENSE
multineuronchat-2025.11.14.dist-info/METADATA
multineuronchat-2025.11.14.dist-info/WHEEL
multineuronchat-2025.11.14.dist-info/top_level.txt
multineuronchat-2025.11.14.dist-info/RECORD
