Metadata-Version: 2.4
Name: multineuronchat
Version: 2025.11.14
Summary: MultiNeuronChat is a Python library for inferring condition‑related changes in synaptic cell‑cell communication from scRNA-/snRNA-Seq datasets in case vs control study designs.
Author-email: Gianluca Volkmer <gianluca.volkmer@ki.se>
License-Expression: GPL-3.0
Requires-Python: >=3.10
License-File: LICENSE
Requires-Dist: numpy==1.26.4
Requires-Dist: pandas==2.3.1
Requires-Dist: xarray==2025.7.1
Requires-Dist: dask==2025.7.0
Requires-Dist: netCDF4==1.7.2
Requires-Dist: bottleneck==1.5.0
Requires-Dist: scipy==1.16.1
Requires-Dist: matplotlib==3.10.5
Requires-Dist: seaborn==0.13.2
Requires-Dist: tqdm==4.67.1
Requires-Dist: loompy==3.0.8
Dynamic: license-file
